[{
  "id": 1,
  "name": "อัล-ฟาติฮะฮ์",
  "verseCount": 7,
  "revelationPlace": "makkah",
  "slug": "al-fatihah",
  "filename": "001.ogg",
  "duration": 87.010833,
  "fileSize": 689921,
  "bitrate": 63433,
  "format": "ogg",
  "codec": "opus"
},{
  "id": 2,
  "name": "อัล-บะเกาะเราะฮ์",
  "verseCount": 286,
  "revelationPlace": "madinah",
  "slug": "al-baqarah",
  "filename": "002.ogg",
  "duration": 13588.600167,
  "fileSize": 114512381,
  "bitrate": 67416,
  "format": "ogg",
  "codec": "opus"
},{
  "id": 3,
  "name": "อาลิ อิมรอน",
  "verseCount": 200,
  "revelationPlace": "madinah",
  "slug": "ali-imran",
  "filename": "003.ogg",
  "duration": 7723.789500,
  "fileSize": 64030700,
  "bitrate": 66320,
  "format": "ogg",
  "codec": "opus"
},{
  "id": 4,
  "name": "อัน-นิสาอ์",
  "verseCount": 176,
  "revelationPlace": "madinah",
  "slug": "an-nisa",
  "filename": "004.ogg",
  "duration": 8280.461500,
  "fileSize": 69610846,
  "bitrate": 67253,
  "format": "ogg",
  "codec": "opus"
},{
  "id": 5,
  "name": "อัล-มาอิดะฮ์",
  "verseCount": 120,
  "revelationPlace": "madinah",
  "slug": "al-maidah",
  "filename": "005.ogg",
  "duration": 6017.976167,
  "fileSize": 49743567,
  "bitrate": 66126,
  "format": "ogg",
  "codec": "opus"
},{
  "id": 6,
  "name": "อัล-อันอาม",
  "verseCount": 165,
  "revelationPlace": "makkah",
  "slug": "al-anam",
  "filename": "006.ogg",
  "duration": 6795.981500,
  "fileSize": 55093777,
  "bitrate": 64854,
  "format": "ogg",
  "codec": "opus"
},{
  "id": 7,
  "name": "อัล-อะอฺรอฟ",
  "verseCount": 206,
  "revelationPlace": "makkah",
  "slug": "al-araf",
  "filename": "007.ogg",
  "duration": 7446.242833,
  "fileSize": 61789883,
  "bitrate": 66385,
  "format": "ogg",
  "codec": "opus"
},{
  "id": 8,
  "name": "อัล-อันฟาล",
  "verseCount": 75,
  "revelationPlace": "madinah",
  "slug": "al-anfal",
  "filename": "008.ogg",
  "duration": 2718.818833,
  "fileSize": 22202808,
  "bitrate": 65330,
  "format": "ogg",
  "codec": "opus"
},{
  "id": 9,
  "name": "อัต-เตาบะฮ์",
  "verseCount": 129,
  "revelationPlace": "madinah",
  "slug": "at-tawbah",
  "filename": "009.ogg",
  "duration": 5690.018833,
  "fileSize": 46605260,
  "bitrate": 65525,
  "format": "ogg",
  "codec": "opus"
},{
  "id": 10,
  "name": "ยูนุส",
  "verseCount": 109,
  "revelationPlace": "makkah",
  "slug": "yunus",
  "filename": "010.ogg",
  "duration": 4079.306833,
  "fileSize": 33697307,
  "bitrate": 66084,
  "format": "ogg",
  "codec": "opus"
},{
  "id": 11,
  "name": "ฮูด",
  "verseCount": 123,
  "revelationPlace": "makkah",
  "slug": "hud",
  "filename": "011.ogg",
  "duration": 4428.920167,
  "fileSize": 36167370,
  "bitrate": 65329,
  "format": "ogg",
  "codec": "opus"
},{
  "id": 12,
  "name": "ยูซุฟ",
  "verseCount": 111,
  "revelationPlace": "makkah",
  "slug": "yusuf",
  "filename": "012.ogg",
  "duration": 3882.936167,
  "fileSize": 31518606,
  "bitrate": 64937,
  "format": "ogg",
  "codec": "opus"
},{
  "id": 13,
  "name": "อัร-เราะอฺด์",
  "verseCount": 43,
  "revelationPlace": "madinah",
  "slug": "ar-rad",
  "filename": "013.ogg",
  "duration": 1879.650833,
  "fileSize": 15480479,
  "bitrate": 65886,
  "format": "ogg",
  "codec": "opus"
},{
  "id": 14,
  "name": "อิบรอฮีม",
  "verseCount": 52,
  "revelationPlace": "makkah",
  "slug": "ibrahim",
  "filename": "014.ogg",
  "duration": 2007.266833,
  "fileSize": 17070907,
  "bitrate": 68036,
  "format": "ogg",
  "codec": "opus"
},{
  "id": 15,
  "name": "อัล-ฮิจรุ",
  "verseCount": 99,
  "revelationPlace": "makkah",
  "slug": "al-hijr",
  "filename": "015.ogg",
  "duration": 1747.149500,
  "fileSize": 14589532,
  "bitrate": 66803,
  "format": "ogg",
  "codec": "opus"
},{
  "id": 16,
  "name": "อัน-นะห์ลุ",
  "verseCount": 128,
  "revelationPlace": "makkah",
  "slug": "an-nahl",
  "filename": "016.ogg",
  "duration": 3858.744167,
  "fileSize": 32359310,
  "bitrate": 67087,
  "format": "ogg",
  "codec": "opus"
},{
  "id": 17,
  "name": "อัล-อิสรออ์",
  "verseCount": 111,
  "revelationPlace": "makkah",
  "slug": "al-isra",
  "filename": "017.ogg",
  "duration": 3307.874833,
  "fileSize": 27697803,
  "bitrate": 66986,
  "format": "ogg",
  "codec": "opus"
},{
  "id": 18,
  "name": "อัล-กะฮฺฟ์",
  "verseCount": 110,
  "revelationPlace": "makkah",
  "slug": "al-kahf",
  "filename": "018.ogg",
  "duration": 3394.680167,
  "fileSize": 28147087,
  "bitrate": 66332,
  "format": "ogg",
  "codec": "opus"
},{
  "id": 19,
  "name": "มัรยัม",
  "verseCount": 98,
  "revelationPlace": "makkah",
  "slug": "maryam",
  "filename": "019.ogg",
  "duration": 2276.536167,
  "fileSize": 18763271,
  "bitrate": 65936,
  "format": "ogg",
  "codec": "opus"
},{
  "id": 20,
  "name": "ตอฮา",
  "verseCount": 135,
  "revelationPlace": "makkah",
  "slug": "taha",
  "filename": "020.ogg",
  "duration": 2955.256167,
  "fileSize": 23936322,
  "bitrate": 64796,
  "format": "ogg",
  "codec": "opus"
},{
  "id": 21,
  "name": "อัล-อัมบิยาอ์",
  "verseCount": 112,
  "revelationPlace": "makkah",
  "slug": "al-anbya",
  "filename": "021.ogg",
  "duration": 3009.229500,
  "fileSize": 24693125,
  "bitrate": 65646,
  "format": "ogg",
  "codec": "opus"
},{
  "id": 22,
  "name": "อัล-ฮัจญ์",
  "verseCount": 78,
  "revelationPlace": "madinah",
  "slug": "al-hajj",
  "filename": "022.ogg",
  "duration": 3030.488167,
  "fileSize": 25272412,
  "bitrate": 66715,
  "format": "ogg",
  "codec": "opus"
},{
  "id": 23,
  "name": "อัล-มุอ์มินูน",
  "verseCount": 118,
  "revelationPlace": "makkah",
  "slug": "al-muminun",
  "filename": "023.ogg",
  "duration": 2648.376167,
  "fileSize": 21878138,
  "bitrate": 66087,
  "format": "ogg",
  "codec": "opus"
},{
  "id": 24,
  "name": "อัน-นูร",
  "verseCount": 64,
  "revelationPlace": "madinah",
  "slug": "an-nur",
  "filename": "024.ogg",
  "duration": 3086.157500,
  "fileSize": 25375253,
  "bitrate": 65778,
  "format": "ogg",
  "codec": "opus"
},{
  "id": 25,
  "name": "อัล-ฟุรกอน",
  "verseCount": 77,
  "revelationPlace": "makkah",
  "slug": "al-furqan",
  "filename": "025.ogg",
  "duration": 2168.973500,
  "fileSize": 17427443,
  "bitrate": 64279,
  "format": "ogg",
  "codec": "opus"
},{
  "id": 26,
  "name": "อัช-ชุอารออ์",
  "verseCount": 227,
  "revelationPlace": "makkah",
  "slug": "ash-shuara",
  "filename": "026.ogg",
  "duration": 3117.282833,
  "fileSize": 25447447,
  "bitrate": 65306,
  "format": "ogg",
  "codec": "opus"
},{
  "id": 27,
  "name": "อัน-นัมล์",
  "verseCount": 93,
  "revelationPlace": "makkah",
  "slug": "an-naml",
  "filename": "027.ogg",
  "duration": 2803.576167,
  "fileSize": 23240646,
  "bitrate": 66317,
  "format": "ogg",
  "codec": "opus"
},{
  "id": 28,
  "name": "อัล-เกาะศอศ",
  "verseCount": 88,
  "revelationPlace": "makkah",
  "slug": "al-qasas",
  "filename": "028.ogg",
  "duration": 3040.696167,
  "fileSize": 24630491,
  "bitrate": 64802,
  "format": "ogg",
  "codec": "opus"
},{
  "id": 29,
  "name": "อัล-อังกาบูต",
  "verseCount": 69,
  "revelationPlace": "makkah",
  "slug": "al-ankabut",
  "filename": "029.ogg",
  "duration": 2630.456167,
  "fileSize": 21721090,
  "bitrate": 66060,
  "format": "ogg",
  "codec": "opus"
},{
  "id": 30,
  "name": "อัร-รูม",
  "verseCount": 60,
  "revelationPlace": "makkah",
  "slug": "ar-rum",
  "filename": "030.ogg",
  "duration": 1925.261500,
  "fileSize": 15782670,
  "bitrate": 65581,
  "format": "ogg",
  "codec": "opus"
},{
  "id": 31,
  "name": "ลุกมาน",
  "verseCount": 34,
  "revelationPlace": "makkah",
  "slug": "luqman",
  "filename": "031.ogg",
  "duration": 1299.789500,
  "fileSize": 10409870,
  "bitrate": 64071,
  "format": "ogg",
  "codec": "opus"
},{
  "id": 32,
  "name": "อัส-สัจดะฮ์",
  "verseCount": 30,
  "revelationPlace": "makkah",
  "slug": "as-sajdah",
  "filename": "032.ogg",
  "duration": 1085.645500,
  "fileSize": 8710681,
  "bitrate": 64188,
  "format": "ogg",
  "codec": "opus"
},{
  "id": 33,
  "name": "อัล-อะห์ซาบ",
  "verseCount": 73,
  "revelationPlace": "madinah",
  "slug": "al-ahzab",
  "filename": "033.ogg",
  "duration": 2936.632167,
  "fileSize": 24070935,
  "bitrate": 65574,
  "format": "ogg",
  "codec": "opus"
},{
  "id": 34,
  "name": "สะบะอ์",
  "verseCount": 54,
  "revelationPlace": "makkah",
  "slug": "saba",
  "filename": "034.ogg",
  "duration": 1991.778833,
  "fileSize": 16231904,
  "bitrate": 65195,
  "format": "ogg",
  "codec": "opus"
},{
  "id": 35,
  "name": "ฟาฏิร",
  "verseCount": 45,
  "revelationPlace": "makkah",
  "slug": "fatir",
  "filename": "035.ogg",
  "duration": 1885.176167,
  "fileSize": 15311249,
  "bitrate": 64975,
  "format": "ogg",
  "codec": "opus"
},{
  "id": 36,
  "name": "ยาสีน",
  "verseCount": 83,
  "revelationPlace": "makkah",
  "slug": "ya-sin",
  "filename": "036.ogg",
  "duration": 1777.058833,
  "fileSize": 14819996,
  "bitrate": 66716,
  "format": "ogg",
  "codec": "opus"
},{
  "id": 37,
  "name": "อัศ-ศ็อฟฟาต",
  "verseCount": 182,
  "revelationPlace": "makkah",
  "slug": "as-saffat",
  "filename": "037.ogg",
  "duration": 2127.010833,
  "fileSize": 17797001,
  "bitrate": 66937,
  "format": "ogg",
  "codec": "opus"
},{
  "id": 38,
  "name": "ศอด",
  "verseCount": 88,
  "revelationPlace": "makkah",
  "slug": "sad",
  "filename": "038.ogg",
  "duration": 1857.421500,
  "fileSize": 15483330,
  "bitrate": 66687,
  "format": "ogg",
  "codec": "opus"
},{
  "id": 39,
  "name": "อัซ-ซุมัร",
  "verseCount": 75,
  "revelationPlace": "makkah",
  "slug": "az-zumar",
  "filename": "039.ogg",
  "duration": 2710.840167,
  "fileSize": 22534313,
  "bitrate": 66501,
  "format": "ogg",
  "codec": "opus"
},{
  "id": 40,
  "name": "ฆอฟิร",
  "verseCount": 85,
  "revelationPlace": "makkah",
  "slug": "ghafir",
  "filename": "040.ogg",
  "duration": 2762.466833,
  "fileSize": 22613127,
  "bitrate": 65486,
  "format": "ogg",
  "codec": "opus"
},{
  "id": 41,
  "name": "ฟุศศิลัต",
  "verseCount": 54,
  "revelationPlace": "makkah",
  "slug": "fussilat",
  "filename": "041.ogg",
  "duration": 1977.016167,
  "fileSize": 16037414,
  "bitrate": 64895,
  "format": "ogg",
  "codec": "opus"
},{
  "id": 42,
  "name": "อัช-ชูรอ",
  "verseCount": 53,
  "revelationPlace": "makkah",
  "slug": "ash-shuraa",
  "filename": "042.ogg",
  "duration": 2058.082833,
  "fileSize": 16700681,
  "bitrate": 64917,
  "format": "ogg",
  "codec": "opus"
},{
  "id": 43,
  "name": "อัซ-ซุครุฟ",
  "verseCount": 89,
  "revelationPlace": "makkah",
  "slug": "az-zukhruf",
  "filename": "043.ogg",
  "duration": 2147.640167,
  "fileSize": 17505228,
  "bitrate": 65207,
  "format": "ogg",
  "codec": "opus"
},{
  "id": 44,
  "name": "อัด-ดุคอน",
  "verseCount": 59,
  "revelationPlace": "makkah",
  "slug": "ad-dukhan",
  "filename": "044.ogg",
  "duration": 1015.672167,
  "fileSize": 8347646,
  "bitrate": 65750,
  "format": "ogg",
  "codec": "opus"
},{
  "id": 45,
  "name": "อัล-ญาษิยะฮ์",
  "verseCount": 37,
  "revelationPlace": "makkah",
  "slug": "al-jathiyah",
  "filename": "045.ogg",
  "duration": 1319.885500,
  "fileSize": 10879758,
  "bitrate": 65943,
  "format": "ogg",
  "codec": "opus"
},{
  "id": 46,
  "name": "อัล-อะห์กอฟ",
  "verseCount": 35,
  "revelationPlace": "makkah",
  "slug": "al-ahqaf",
  "filename": "046.ogg",
  "duration": 1579.853500,
  "fileSize": 12906649,
  "bitrate": 65356,
  "format": "ogg",
  "codec": "opus"
},{
  "id": 47,
  "name": "มุฮัมมัด",
  "verseCount": 38,
  "revelationPlace": "madinah",
  "slug": "muhammad",
  "filename": "047.ogg",
  "duration": 1387.960167,
  "fileSize": 11298985,
  "bitrate": 65125,
  "format": "ogg",
  "codec": "opus"
},{
  "id": 48,
  "name": "อัล-ฟัตห์",
  "verseCount": 29,
  "revelationPlace": "madinah",
  "slug": "al-fath",
  "filename": "048.ogg",
  "duration": 1460.088167,
  "fileSize": 11763980,
  "bitrate": 64456,
  "format": "ogg",
  "codec": "opus"
},{
  "id": 49,
  "name": "อัล-ฮุจุรอต",
  "verseCount": 18,
  "revelationPlace": "madinah",
  "slug": "al-hujurat",
  "filename": "049.ogg",
  "duration": 1054.818833,
  "fileSize": 8460539,
  "bitrate": 64166,
  "format": "ogg",
  "codec": "opus"
},{
  "id": 50,
  "name": "กอฟ",
  "verseCount": 45,
  "revelationPlace": "makkah",
  "slug": "qaf",
  "filename": "050.ogg",
  "duration": 1048.141500,
  "fileSize": 8480787,
  "bitrate": 64730,
  "format": "ogg",
  "codec": "opus"
},{
  "id": 51,
  "name": "อัซ-ซาริยาต",
  "verseCount": 60,
  "revelationPlace": "makkah",
  "slug": "adh-dhariyat",
  "filename": "051.ogg",
  "duration": 1068.706833,
  "fileSize": 8697100,
  "bitrate": 65103,
  "format": "ogg",
  "codec": "opus"
},{
  "id": 52,
  "name": "อัฏ-ฏูร",
  "verseCount": 49,
  "revelationPlace": "makkah",
  "slug": "at-tur",
  "filename": "052.ogg",
  "duration": 910.477500,
  "fileSize": 7321900,
  "bitrate": 64334,
  "format": "ogg",
  "codec": "opus"
},{
  "id": 53,
  "name": "อัน-นัจม์",
  "verseCount": 62,
  "revelationPlace": "makkah",
  "slug": "an-najm",
  "filename": "053.ogg",
  "duration": 993.229500,
  "fileSize": 7905997,
  "bitrate": 63679,
  "format": "ogg",
  "codec": "opus"
},{
  "id": 54,
  "name": "อัล-เกาะมัร",
  "verseCount": 55,
  "revelationPlace": "makkah",
  "slug": "al-qamar",
  "filename": "054.ogg",
  "duration": 1090.722833,
  "fileSize": 8725567,
  "bitrate": 63998,
  "format": "ogg",
  "codec": "opus"
},{
  "id": 55,
  "name": "อัร-เราะห์มาน",
  "verseCount": 78,
  "revelationPlace": "madinah",
  "slug": "ar-rahman",
  "filename": "055.ogg",
  "duration": 1390.925500,
  "fileSize": 11301355,
  "bitrate": 65000,
  "format": "ogg",
  "codec": "opus"
},{
  "id": 56,
  "name": "อัล-วากิอะฮ์",
  "verseCount": 96,
  "revelationPlace": "makkah",
  "slug": "al-waqiah",
  "filename": "056.ogg",
  "duration": 1054.562833,
  "fileSize": 8700751,
  "bitrate": 66004,
  "format": "ogg",
  "codec": "opus"
},{
  "id": 57,
  "name": "อัล-ฮะดีด",
  "verseCount": 29,
  "revelationPlace": "madinah",
  "slug": "al-hadid",
  "filename": "057.ogg",
  "duration": 1535.928167,
  "fileSize": 12559537,
  "bitrate": 65417,
  "format": "ogg",
  "codec": "opus"
},{
  "id": 58,
  "name": "อัล-มุจาดะละฮ์",
  "verseCount": 22,
  "revelationPlace": "madinah",
  "slug": "al-mujadila",
  "filename": "058.ogg",
  "duration": 1349.581500,
  "fileSize": 10885369,
  "bitrate": 64525,
  "format": "ogg",
  "codec": "opus"
},{
  "id": 59,
  "name": "อัล-ฮัชร์",
  "verseCount": 24,
  "revelationPlace": "madinah",
  "slug": "al-hashr",
  "filename": "059.ogg",
  "duration": 1251.042833,
  "fileSize": 10052813,
  "bitrate": 64284,
  "format": "ogg",
  "codec": "opus"
},{
  "id": 60,
  "name": "อัล-มุมตะฮินะฮ์",
  "verseCount": 13,
  "revelationPlace": "madinah",
  "slug": "al-mumtahanah",
  "filename": "060.ogg",
  "duration": 1220.984167,
  "fileSize": 9994049,
  "bitrate": 65481,
  "format": "ogg",
  "codec": "opus"
},{
  "id": 61,
  "name": "อัศ-ศ็อฟฟ์",
  "verseCount": 14,
  "revelationPlace": "madinah",
  "slug": "as-saf",
  "filename": "061.ogg",
  "duration": 703.437500,
  "fileSize": 5610195,
  "bitrate": 63803,
  "format": "ogg",
  "codec": "opus"
},{
  "id": 62,
  "name": "อัล-ญุมุอะฮ์",
  "verseCount": 11,
  "revelationPlace": "madinah",
  "slug": "al-jumuah",
  "filename": "062.ogg",
  "duration": 471.608167,
  "fileSize": 3786787,
  "bitrate": 64236,
  "format": "ogg",
  "codec": "opus"
},{
  "id": 63,
  "name": "อัล-มุนาฟิกูน",
  "verseCount": 11,
  "revelationPlace": "madinah",
  "slug": "al-munafiqun",
  "filename": "063.ogg",
  "duration": 716.578833,
  "fileSize": 5621286,
  "bitrate": 62756,
  "format": "ogg",
  "codec": "opus"
},{
  "id": 64,
  "name": "อัต-ตะฆอบุน",
  "verseCount": 18,
  "revelationPlace": "madinah",
  "slug": "at-taghabun",
  "filename": "064.ogg",
  "duration": 672.162833,
  "fileSize": 5374685,
  "bitrate": 63968,
  "format": "ogg",
  "codec": "opus"
},{
  "id": 65,
  "name": "อัฏ-เฏาะลาก",
  "verseCount": 12,
  "revelationPlace": "madinah",
  "slug": "at-talaq",
  "filename": "065.ogg",
  "duration": 806.626833,
  "fileSize": 6436904,
  "bitrate": 63840,
  "format": "ogg",
  "codec": "opus"
},{
  "id": 66,
  "name": "อัต-ตะห์รีม",
  "verseCount": 12,
  "revelationPlace": "madinah",
  "slug": "at-tahrim",
  "filename": "066.ogg",
  "duration": 835.021500,
  "fileSize": 6609735,
  "bitrate": 63325,
  "format": "ogg",
  "codec": "opus"
},{
  "id": 67,
  "name": "อัล-มุลก์",
  "verseCount": 30,
  "revelationPlace": "makkah",
  "slug": "al-mulk",
  "filename": "067.ogg",
  "duration": 946.146833,
  "fileSize": 7531698,
  "bitrate": 63683,
  "format": "ogg",
  "codec": "opus"
},{
  "id": 68,
  "name": "อัล-เกาะลัม",
  "verseCount": 52,
  "revelationPlace": "makkah",
  "slug": "al-qalam",
  "filename": "068.ogg",
  "duration": 1000.034833,
  "fileSize": 8010957,
  "bitrate": 64085,
  "format": "ogg",
  "codec": "opus"
},{
  "id": 69,
  "name": "อัล-ฮากเกาะฮ์",
  "verseCount": 52,
  "revelationPlace": "makkah",
  "slug": "al-haqqah",
  "filename": "069.ogg",
  "duration": 882.018833,
  "fileSize": 7013583,
  "bitrate": 63613,
  "format": "ogg",
  "codec": "opus"
},{
  "id": 70,
  "name": "อัล-มะอาริจ",
  "verseCount": 44,
  "revelationPlace": "makkah",
  "slug": "al-maarij",
  "filename": "070.ogg",
  "duration": 785.869500,
  "fileSize": 6307275,
  "bitrate": 64206,
  "format": "ogg",
  "codec": "opus"
},{
  "id": 71,
  "name": "นูห์",
  "verseCount": 28,
  "revelationPlace": "makkah",
  "slug": "nuh",
  "filename": "071.ogg",
  "duration": 780.365500,
  "fileSize": 6199913,
  "bitrate": 63559,
  "format": "ogg",
  "codec": "opus"
},{
  "id": 72,
  "name": "อัล-ญินน์",
  "verseCount": 28,
  "revelationPlace": "makkah",
  "slug": "al-jinn",
  "filename": "072.ogg",
  "duration": 867.469500,
  "fileSize": 6952744,
  "bitrate": 64119,
  "format": "ogg",
  "codec": "opus"
},{
  "id": 73,
  "name": "อัล-มุซซัมมิล",
  "verseCount": 20,
  "revelationPlace": "makkah",
  "slug": "al-muzzammil",
  "filename": "073.ogg",
  "duration": 660.152167,
  "fileSize": 5283528,
  "bitrate": 64028,
  "format": "ogg",
  "codec": "opus"
},{
  "id": 74,
  "name": "อัล-มุดดัษษิร",
  "verseCount": 56,
  "revelationPlace": "makkah",
  "slug": "al-muddaththir",
  "filename": "074.ogg",
  "duration": 857.016167,
  "fileSize": 6841407,
  "bitrate": 63862,
  "format": "ogg",
  "codec": "opus"
},{
  "id": 75,
  "name": "อัล-กิยามะฮ์",
  "verseCount": 40,
  "revelationPlace": "makkah",
  "slug": "al-qiyamah",
  "filename": "075.ogg",
  "duration": 636.365500,
  "fileSize": 5038451,
  "bitrate": 63340,
  "format": "ogg",
  "codec": "opus"
},{
  "id": 76,
  "name": "อัล-อินซาน",
  "verseCount": 31,
  "revelationPlace": "madinah",
  "slug": "al-insan",
  "filename": "076.ogg",
  "duration": 833.656167,
  "fileSize": 6714662,
  "bitrate": 64435,
  "format": "ogg",
  "codec": "opus"
},{
  "id": 77,
  "name": "อัล-มุรสะลาต",
  "verseCount": 50,
  "revelationPlace": "makkah",
  "slug": "al-mursalat",
  "filename": "077.ogg",
  "duration": 722.253500,
  "fileSize": 5853888,
  "bitrate": 64840,
  "format": "ogg",
  "codec": "opus"
},{
  "id": 78,
  "name": "อัน-นะบะอ์",
  "verseCount": 40,
  "revelationPlace": "makkah",
  "slug": "an-naba",
  "filename": "078.ogg",
  "duration": 651.106833,
  "fileSize": 5339605,
  "bitrate": 65606,
  "format": "ogg",
  "codec": "opus"
},{
  "id": 79,
  "name": "อัน-นาซิอาต",
  "verseCount": 46,
  "revelationPlace": "makkah",
  "slug": "an-naziat",
  "filename": "079.ogg",
  "duration": 670.136167,
  "fileSize": 5380236,
  "bitrate": 64228,
  "format": "ogg",
  "codec": "opus"
},{
  "id": 80,
  "name": "อะบะสะ",
  "verseCount": 42,
  "revelationPlace": "makkah",
  "slug": "abasa",
  "filename": "080.ogg",
  "duration": 527.117500,
  "fileSize": 4218277,
  "bitrate": 64020,
  "format": "ogg",
  "codec": "opus"
},{
  "id": 81,
  "name": "อัต-ตักวีน",
  "verseCount": 29,
  "revelationPlace": "makkah",
  "slug": "at-takwir",
  "filename": "081.ogg",
  "duration": 390.989500,
  "fileSize": 3131333,
  "bitrate": 64069,
  "format": "ogg",
  "codec": "opus"
},{
  "id": 82,
  "name": "อัล-อินฟิฏอร",
  "verseCount": 19,
  "revelationPlace": "makkah",
  "slug": "al-infitar",
  "filename": "082.ogg",
  "duration": 391.266833,
  "fileSize": 3122903,
  "bitrate": 63852,
  "format": "ogg",
  "codec": "opus"
},{
  "id": 83,
  "name": "อัล-มุฏ็อฟฟิฟีน",
  "verseCount": 36,
  "revelationPlace": "makkah",
  "slug": "al-mutaffifin",
  "filename": "083.ogg",
  "duration": 592.461500,
  "fileSize": 4825397,
  "bitrate": 65157,
  "format": "ogg",
  "codec": "opus"
},{
  "id": 84,
  "name": "อัล-อินชิกอก",
  "verseCount": 25,
  "revelationPlace": "makkah",
  "slug": "al-inshiqaq",
  "filename": "084.ogg",
  "duration": 415.053500,
  "fileSize": 3327735,
  "bitrate": 64140,
  "format": "ogg",
  "codec": "opus"
},{
  "id": 85,
  "name": "อัล-บุรูจ",
  "verseCount": 22,
  "revelationPlace": "makkah",
  "slug": "al-buruj",
  "filename": "085.ogg",
  "duration": 427.661500,
  "fileSize": 3444461,
  "bitrate": 64433,
  "format": "ogg",
  "codec": "opus"
},{
  "id": 86,
  "name": "อัฏ-ฏอริก",
  "verseCount": 17,
  "revelationPlace": "makkah",
  "slug": "at-tariq",
  "filename": "086.ogg",
  "duration": 338.573500,
  "fileSize": 2666001,
  "bitrate": 62993,
  "format": "ogg",
  "codec": "opus"
},{
  "id": 87,
  "name": "อัล-อะอฺลา",
  "verseCount": 19,
  "revelationPlace": "makkah",
  "slug": "al-ala",
  "filename": "087.ogg",
  "duration": 318.157500,
  "fileSize": 2517851,
  "bitrate": 63310,
  "format": "ogg",
  "codec": "opus"
},{
  "id": 88,
  "name": "อัล-ฆอชิยะฮ์",
  "verseCount": 26,
  "revelationPlace": "makkah",
  "slug": "al-ghashiyah",
  "filename": "088.ogg",
  "duration": 282.552167,
  "fileSize": 2298647,
  "bitrate": 65082,
  "format": "ogg",
  "codec": "opus"
},{
  "id": 89,
  "name": "อัล-ฟัจร์",
  "verseCount": 30,
  "revelationPlace": "makkah",
  "slug": "al-fajr",
  "filename": "089.ogg",
  "duration": 421.581500,
  "fileSize": 3425513,
  "bitrate": 65003,
  "format": "ogg",
  "codec": "opus"
},{
  "id": 90,
  "name": "อัล-บะลัด",
  "verseCount": 20,
  "revelationPlace": "makkah",
  "slug": "al-balad",
  "filename": "090.ogg",
  "duration": 304.546833,
  "fileSize": 2403284,
  "bitrate": 63130,
  "format": "ogg",
  "codec": "opus"
},{
  "id": 91,
  "name": "อัช-ชัมส์",
  "verseCount": 15,
  "revelationPlace": "makkah",
  "slug": "ash-shams",
  "filename": "091.ogg",
  "duration": 274.466833,
  "fileSize": 2132652,
  "bitrate": 62161,
  "format": "ogg",
  "codec": "opus"
},{
  "id": 92,
  "name": "อัล-ลัยล์",
  "verseCount": 21,
  "revelationPlace": "makkah",
  "slug": "al-layl",
  "filename": "092.ogg",
  "duration": 357.261500,
  "fileSize": 2828004,
  "bitrate": 63326,
  "format": "ogg",
  "codec": "opus"
},{
  "id": 93,
  "name": "อัฎ-ฎุฮา",
  "verseCount": 11,
  "revelationPlace": "makkah",
  "slug": "ad-duhaa",
  "filename": "093.ogg",
  "duration": 264.205500,
  "fileSize": 2056270,
  "bitrate": 62262,
  "format": "ogg",
  "codec": "opus"
},{
  "id": 94,
  "name": "อัล-อินชิรอห์",
  "verseCount": 8,
  "revelationPlace": "makkah",
  "slug": "ash-sharh",
  "filename": "094.ogg",
  "duration": 217.869500,
  "fileSize": 1636508,
  "bitrate": 60091,
  "format": "ogg",
  "codec": "opus"
},{
  "id": 95,
  "name": "อัต-ตีน",
  "verseCount": 8,
  "revelationPlace": "makkah",
  "slug": "at-tin",
  "filename": "095.ogg",
  "duration": 200.290833,
  "fileSize": 1572730,
  "bitrate": 62817,
  "format": "ogg",
  "codec": "opus"
},{
  "id": 96,
  "name": "อัล-อะลัก",
  "verseCount": 19,
  "revelationPlace": "makkah",
  "slug": "al-alaq",
  "filename": "096.ogg",
  "duration": 329.485500,
  "fileSize": 2594512,
  "bitrate": 62995,
  "format": "ogg",
  "codec": "opus"
},{
  "id": 97,
  "name": "อัล-ก็อดร์",
  "verseCount": 5,
  "revelationPlace": "makkah",
  "slug": "al-qadr",
  "filename": "097.ogg",
  "duration": 126.882833,
  "fileSize": 987389,
  "bitrate": 62255,
  "format": "ogg",
  "codec": "opus"
},{
  "id": 98,
  "name": "อัล-บัยยินะฮ์",
  "verseCount": 8,
  "revelationPlace": "madinah",
  "slug": "al-bayyinah",
  "filename": "098.ogg",
  "duration": 346.914833,
  "fileSize": 2792734,
  "bitrate": 64401,
  "format": "ogg",
  "codec": "opus"
},{
  "id": 99,
  "name": "อัซ-ซัลซะละฮ์",
  "verseCount": 8,
  "revelationPlace": "madinah",
  "slug": "az-zalzalah",
  "filename": "099.ogg",
  "duration": 167.736167,
  "fileSize": 1305424,
  "bitrate": 62260,
  "format": "ogg",
  "codec": "opus"
},{
  "id": 100,
  "name": "อัล-อาดิยาต",
  "verseCount": 11,
  "revelationPlace": "makkah",
  "slug": "al-adiyat",
  "filename": "100.ogg",
  "duration": 203.896167,
  "fileSize": 1607559,
  "bitrate": 63073,
  "format": "ogg",
  "codec": "opus"
},{
  "id": 101,
  "name": "อัล-กอริอะฮ์",
  "verseCount": 11,
  "revelationPlace": "makkah",
  "slug": "al-qariah",
  "filename": "101.ogg",
  "duration": 181.986833,
  "fileSize": 1427913,
  "bitrate": 62769,
  "format": "ogg",
  "codec": "opus"
},{
  "id": 102,
  "name": "อัต-ตะกาษุร",
  "verseCount": 8,
  "revelationPlace": "makkah",
  "slug": "at-takathur",
  "filename": "102.ogg",
  "duration": 158.349500,
  "fileSize": 1239591,
  "bitrate": 62625,
  "format": "ogg",
  "codec": "opus"
},{
  "id": 103,
  "name": "อัล-อัศร์",
  "verseCount": 3,
  "revelationPlace": "makkah",
  "slug": "al-asr",
  "filename": "103.ogg",
  "duration": 124.728167,
  "fileSize": 944490,
  "bitrate": 60579,
  "format": "ogg",
  "codec": "opus"
},{
  "id": 104,
  "name": "อัล-ฮุมะซะฮ์",
  "verseCount": 9,
  "revelationPlace": "makkah",
  "slug": "al-humazah",
  "filename": "104.ogg",
  "duration": 157.346833,
  "fileSize": 1212720,
  "bitrate": 61658,
  "format": "ogg",
  "codec": "opus"
},{
  "id": 105,
  "name": "อัล-ฟีล",
  "verseCount": 5,
  "revelationPlace": "makkah",
  "slug": "al-fil",
  "filename": "105.ogg",
  "duration": 135.032167,
  "fileSize": 1040433,
  "bitrate": 61640,
  "format": "ogg",
  "codec": "opus"
},{
  "id": 106,
  "name": "กุร็อยช์",
  "verseCount": 4,
  "revelationPlace": "makkah",
  "slug": "quraysh",
  "filename": "106.ogg",
  "duration": 116.856167,
  "fileSize": 908471,
  "bitrate": 62194,
  "format": "ogg",
  "codec": "opus"
},{
  "id": 107,
  "name": "อัล-มาอูน",
  "verseCount": 7,
  "revelationPlace": "makkah",
  "slug": "al-maun",
  "filename": "107.ogg",
  "duration": 197.090833,
  "fileSize": 1540919,
  "bitrate": 62546,
  "format": "ogg",
  "codec": "opus"
},{
  "id": 108,
  "name": "อัล-เกาษัร",
  "verseCount": 3,
  "revelationPlace": "makkah",
  "slug": "al-kawthar",
  "filename": "108.ogg",
  "duration": 137.933500,
  "fileSize": 1056463,
  "bitrate": 61273,
  "format": "ogg",
  "codec": "opus"
},{
  "id": 109,
  "name": "อัล-กาฟิรูน",
  "verseCount": 6,
  "revelationPlace": "makkah",
  "slug": "al-kafirun",
  "filename": "109.ogg",
  "duration": 175.074833,
  "fileSize": 1381270,
  "bitrate": 63116,
  "format": "ogg",
  "codec": "opus"
},{
  "id": 110,
  "name": "อัน-นัศร์",
  "verseCount": 3,
  "revelationPlace": "madinah",
  "slug": "an-nasr",
  "filename": "110.ogg",
  "duration": 135.864167,
  "fileSize": 1038547,
  "bitrate": 61152,
  "format": "ogg",
  "codec": "opus"
},{
  "id": 111,
  "name": "อัล-มะสัด",
  "verseCount": 5,
  "revelationPlace": "makkah",
  "slug": "al-masad",
  "filename": "111.ogg",
  "duration": 155.661500,
  "fileSize": 1208232,
  "bitrate": 62095,
  "format": "ogg",
  "codec": "opus"
},{
  "id": 112,
  "name": "อัล-อิคลาศ",
  "verseCount": 4,
  "revelationPlace": "makkah",
  "slug": "al-ikhlas",
  "filename": "112.ogg",
  "duration": 97.506833,
  "fileSize": 735528,
  "bitrate": 60346,
  "format": "ogg",
  "codec": "opus"
},{
  "id": 113,
  "name": "อัล-ฟะลัก",
  "verseCount": 5,
  "revelationPlace": "makkah",
  "slug": "al-falaq",
  "filename": "113.ogg",
  "duration": 119.778833,
  "fileSize": 923324,
  "bitrate": 61668,
  "format": "ogg",
  "codec": "opus"
},{
  "id": 114,
  "name": "อัน-นาส",
  "verseCount": 6,
  "revelationPlace": "makkah",
  "slug": "an-nas",
  "filename": "114.ogg",
  "duration": 124.621500,
  "fileSize": 967158,
  "bitrate": 62086,
  "format": "ogg",
  "codec": "opus"
}]
